ophydregistry/__init__.py
ophydregistry/_typing.py
ophydregistry/exceptions.py
ophydregistry/py.typed
ophydregistry/registry.py
ophydregistry/tests/test_instrument_registry.py
ophyd_registry-2.0.0.dist-info/METADATA
ophyd_registry-2.0.0.dist-info/WHEEL
ophyd_registry-2.0.0.dist-info/top_level.txt
ophyd_registry-2.0.0.dist-info/RECORD
