Metadata-Version: 2.2
Name: ophyd-registry
Version: 2.0.0
Summary: A registry to keep track of, and retrieve, Ophyd objects.
Author-email: Mark Wolfman <wolfman@anl.gov>
Project-URL: Homepage, https://github.com/spc-group/ophyd-registry
Project-URL: Bug Tracker, https://github.com/spc-group/ophyd-registry/issues
Keywords: synchrotron,xray,bluesky
Classifier: Programming Language :: Python :: 3
Classifier: Operating System :: OS Independent
Classifier: Development Status :: 5 - Production/Stable
Classifier: Topic :: Scientific/Engineering
Classifier: Topic :: System :: Hardware
Requires-Python: >=3.9
Requires-Dist: ophyd
Provides-Extra: dev
Requires-Dist: ophyd_async; extra == "dev"
Requires-Dist: black; extra == "dev"
Requires-Dist: isort; extra == "dev"
Requires-Dist: pytest; extra == "dev"
Requires-Dist: pytest-mypy; extra == "dev"
Requires-Dist: build; extra == "dev"
Requires-Dist: twine; extra == "dev"
Requires-Dist: flake8; extra == "dev"
Requires-Dist: ruff; extra == "dev"
Requires-Dist: pytest-mock; extra == "dev"
Requires-Dist: caproto; extra == "dev"
